ezrequest/__init__.py
ezrequest/_version.py
ezrequest/ezrequest.py
tests/__init__.py
tests/test_ezrequest.py
ezrequest-2020.200.757.dist-info/LICENSE
ezrequest-2020.200.757.dist-info/METADATA
ezrequest-2020.200.757.dist-info/WHEEL
ezrequest-2020.200.757.dist-info/top_level.txt
ezrequest-2020.200.757.dist-info/RECORD
