Metadata-Version: 2.1
Name: ezrequest
Version: 2020.200.757
Summary: UNKNOWN
Home-page: https://github.com/coderepocenter/ezrequest.git
Author: Mohammad Abouali
Author-email: maboualidev@gmail.com
License: UNKNOWN
Platform: UNKNOWN
Classifier: Programming Language :: Python :: 3
Classifier: Operating System :: OS Independent
Requires-Python: >=3.6
Requires-Dist: requests
Requires-Dist: numpy
